syscovis/__init__.py
syscovis/plotter/plots/plotter.html
syscovis/plotter/plots/plotter.svg
syscovis/plotter/plotter.py
syscovis/plotter/test_plotter.py
syscovis/py.typed
syscovis-0.1.1b1.dist-info/WHEEL
syscovis-0.1.1b1.dist-info/METADATA
syscovis-0.1.1b1.dist-info/RECORD
